build_harness/VERSION
build_harness/__init__.py
build_harness/_base_exception.py
build_harness/_default_values.py
build_harness/_utility.py
build_harness/_version.py
build_harness/entrypoint.py
build_harness/project.py
build_harness/py.typed
build_harness/typing.py
build_harness/commands/__init__.py
build_harness/commands/_declarations.py
build_harness/commands/_publish_flow.py
build_harness/commands/_release_flow.py
build_harness/commands/_release_id.py
build_harness/commands/analysis.py
build_harness/commands/bootstrap.py
build_harness/commands/build_harness_group.py
build_harness/commands/code_style.py
build_harness/commands/dependencies.py
build_harness/commands/publishing.py
build_harness/commands/state.py
build_harness/commands/unit_tests.py
build_harness/commands/wheel.py
build_harness/commands/bdd/__init__.py
build_harness/commands/bdd/bdd_group.py
build_harness/commands/bdd/run_tests.py
build_harness/commands/bdd/snippets.py
build_harness/commands/bdd/tags.py
build_harness/templates/cookiecutter.json
build_harness/templates/hooks/post_gen_project.py
build_harness/templates/hooks/pre_gen_project.py
build_harness/templates/{{cookiecutter.project_slug}}/.flake8
build_harness/templates/{{cookiecutter.project_slug}}/.gitignore
build_harness/templates/{{cookiecutter.project_slug}}/.gitlab-ci.yml
build_harness/templates/{{cookiecutter.project_slug}}/.pre-commit-config.yaml
build_harness/templates/{{cookiecutter.project_slug}}/Makefile
build_harness/templates/{{cookiecutter.project_slug}}/README.rst
build_harness/templates/{{cookiecutter.project_slug}}/pyproject.toml
build_harness/templates/{{cookiecutter.project_slug}}/setup.cfg
build_harness/templates/{{cookiecutter.project_slug}}/features/__init__.py
build_harness/templates/{{cookiecutter.project_slug}}/features/steps/__init__.py
build_harness/templates/{{cookiecutter.project_slug}}/tests/__init__.py
build_harness/templates/{{cookiecutter.project_slug}}/tests/ci/__init__.py
build_harness-3.0.1.dist-info/entry_points.txt
build_harness-3.0.1.dist-info/licenses/LICENSE
build_harness-3.0.1.dist-info/WHEEL
build_harness-3.0.1.dist-info/METADATA
build_harness-3.0.1.dist-info/RECORD
