Metadata-Version: 2.4
Name: build_harness
Version: 3.0.1
Summary: CI build harness embodying best practices for Python projects.
Author-email: Russell Smiley <russell@blueskyjunkie.ca>
Requires-Python: >=3.8
Classifier: Intended Audience :: Developers
Classifier: License :: OSI Approved :: MIT License
Classifier: Programming Language :: Python :: 3 :: Only
Classifier: Topic :: System :: Software Distribution
Classifier: Typing :: Typed
License-File: LICENSE
Requires-Dist: behave >=1.2.6, <2
Requires-Dist: black >=24.4.2, <25
Requires-Dist: click_logging_config >=2.1.1
Requires-Dist: cookiecutter >=2.1.1, <3
Requires-Dist: flake8 >=7.3, <8
Requires-Dist: flake8-annotations >=3.0.1, <4
Requires-Dist: flake8-bandit >=4.1.1, <5
Requires-Dist: flake8-bugbear >=23.7.10, <24
Requires-Dist: flake8-comprehensions >=3.14.0, <4
Requires-Dist: flake8-docstrings >=1.7.0, <2
Requires-Dist: flit >=3.2.0, <4
Requires-Dist: gitpython >=3.1.24, <4
Requires-Dist: isort >=5.12, <6
Requires-Dist: mypy >=1.10.0
Requires-Dist: packaging >=24
Requires-Dist: parver >=0.3.1, <1
Requires-Dist: pip >=22.0.4, <25
Requires-Dist: pre_commit >=2.17.0, <4
Requires-Dist: pydantic >=1.9.0, <3
Requires-Dist: toml >=0.10.2, <1
Requires-Dist: twine >=6.1, <7
Requires-Dist: wheel >=0.43.0, <1
Requires-Dist: pygments >=2.11.2, <3
Requires-Dist: typing-extensions; python_version <'3.8'
Requires-Dist: invoke >=2.2.0, <3 ; extra == "dev"
Requires-Dist: mutmut >=2.1.0, <3 ; extra == "dev"
Requires-Dist: pipenv >=2021.5.29 ; extra == "dev"
Requires-Dist: types-toml >=0.10.4, <1 ; extra == "dev"
Requires-Dist: sphinx <7.2.6 ; extra == "doc" and ( python_version < '3.9')
Requires-Dist: sphinx >=7.2.6, <8 ; extra == "doc" and ( python_version >= '3.9')
Requires-Dist: sphinx_rtd_theme >=2.0, <3 ; extra == "doc"
Requires-Dist: pytest >=7.4.3, <8 ; extra == "test"
Requires-Dist: pytest-cov >=4.1, <5 ; extra == "test"
Requires-Dist: pytest-mock >=3.12.0, <4 ; extra == "test"
Project-URL: Source, https://gitlab.com/ci-cd-devops/build_harness
Provides-Extra: dev
Provides-Extra: doc
Provides-Extra: test
